bin/__init__.py
bin/nPhase.py
bin/nPhaseCleaning.py
bin/nPhasePipeline.py
bin/nPhasePipelineFunctions.py
nPhase-1.2.1.dist-info/LICENSE
nPhase-1.2.1.dist-info/METADATA
nPhase-1.2.1.dist-info/WHEEL
nPhase-1.2.1.dist-info/entry_points.txt
nPhase-1.2.1.dist-info/top_level.txt
nPhase-1.2.1.dist-info/RECORD
