Metadata-Version: 2.1
Name: nPhase
Version: 1.2.1
Summary: nPhase is a command line ploidy agnostic phasing pipeline and algorithm which phases samples of any ploidy with sequence alignment of long and short read data to a reference sequence.
Home-page: https://https://github.com/nPhasePipeline/nPhase
Author: Omar Abou Saada
Author-email: omaroakheart@gmail.com
Classifier: Programming Language :: Python :: 3.8
Classifier: License :: OSI Approved :: GNU General Public License v3 (GPLv3)
Classifier: Operating System :: OS Independent
Classifier: Development Status :: 5 - Production/Stable
Classifier: Topic :: Scientific/Engineering :: Bio-Informatics
Requires-Python: >=3.8
License-File: LICENSE
Requires-Dist: plotnine
Requires-Dist: sortedcontainers
